photomaker/__init__.py
photomaker/model.py
photomaker/pipeline.py
photomakerv-0.1.0.dist-info/LICENSE
photomakerv-0.1.0.dist-info/METADATA
photomakerv-0.1.0.dist-info/WHEEL
photomakerv-0.1.0.dist-info/RECORD
