Metadata-Version: 2.1
Name: photomakerv
Version: 0.1.0
Summary: PhotoMaker: Customizing Realistic Human Photos via Stacked ID Embedding
License: Apache-2.0
Author: Li, Zhen
Requires-Python: >=3.7
Classifier: License :: OSI Approved :: Apache Software License
Classifier: Programming Language :: Python :: 3
Classifier: Programming Language :: Python :: 3.7
Classifier: Programming Language :: Python :: 3.8
Classifier: Programming Language :: Python :: 3.9
Classifier: Programming Language :: Python :: 3.10
Classifier: Programming Language :: Python :: 3.11
Classifier: Programming Language :: Python :: 3.12
